h2o_autodoc/build_info.cpython-39-x86_64-linux-gnu.so
h2o_autodoc/run_autodoc.cpython-39-x86_64-linux-gnu.so
h2o_autodoc/build_info.py
h2o_autodoc/run_autodoc.py
h2o_autodoc/__init__.py
h2o_autodoc/__init__.cpython-39-x86_64-linux-gnu.so
h2o_autodoc/config/config.cpython-39-x86_64-linux-gnu.so
h2o_autodoc/config/__init__.cpython-39-x86_64-linux-gnu.so
h2o_autodoc/fonts/TakaoPGothic.ttf
h2o_autodoc/driverlessai/__init__.cpython-39-x86_64-linux-gnu.so
h2o_autodoc/utils/utils.cpython-39-x86_64-linux-gnu.so
h2o_autodoc/utils/template_rendering.cpython-39-x86_64-linux-gnu.so
h2o_autodoc/utils/separators.cpython-39-x86_64-linux-gnu.so
h2o_autodoc/utils/converter.cpython-39-x86_64-linux-gnu.so
h2o_autodoc/utils/autoreport_plots.cpython-39-x86_64-linux-gnu.so
h2o_autodoc/utils/section.cpython-39-x86_64-linux-gnu.so
h2o_autodoc/utils/decorators.cpython-39-x86_64-linux-gnu.so
h2o_autodoc/utils/data.cpython-39-x86_64-linux-gnu.so
h2o_autodoc/utils/predictions.cpython-39-x86_64-linux-gnu.so
h2o_autodoc/utils/s3_helper.cpython-39-x86_64-linux-gnu.so
h2o_autodoc/utils/recipes.cpython-39-x86_64-linux-gnu.so
h2o_autodoc/utils/storage_connector.cpython-39-x86_64-linux-gnu.so
h2o_autodoc/utils/git_helper.cpython-39-x86_64-linux-gnu.so
h2o_autodoc/utils/__init__.cpython-39-x86_64-linux-gnu.so
h2o_autodoc/scikit/utils.cpython-39-x86_64-linux-gnu.so
h2o_autodoc/scikit/scikit_final_model.cpython-39-x86_64-linux-gnu.so
h2o_autodoc/scikit/scikit_feature_importance.cpython-39-x86_64-linux-gnu.so
h2o_autodoc/scikit/scikit_parms_info.cpython-39-x86_64-linux-gnu.so
h2o_autodoc/scikit/scikit_predictions.cpython-39-x86_64-linux-gnu.so
h2o_autodoc/scikit/scikit_model_performance.cpython-39-x86_64-linux-gnu.so
h2o_autodoc/scikit/scikit_version_info.cpython-39-x86_64-linux-gnu.so
h2o_autodoc/scikit/scikit_experiment_overview.cpython-39-x86_64-linux-gnu.so
h2o_autodoc/scikit/scikit_validation_strategy.cpython-39-x86_64-linux-gnu.so
h2o_autodoc-1.1.0.dist-info/zip-safe
h2o_autodoc-1.1.0.dist-info/top_level.txt
h2o_autodoc-1.1.0.dist-info/entry_points.txt
h2o_autodoc-1.1.0.dist-info/METADATA
h2o_autodoc-1.1.0.dist-info/RECORD
h2o_autodoc-1.1.0.dist-info/WHEEL
h2o_autodoc-1.1.0.dist-info/LICENSE
