Metadata-Version: 2.1
Name: h2o-autodoc
Version: 1.1.0
Summary: Create a machine learning model documentation
Home-page: https://www.h2o.ai/products/h2o-autodoc/
Author: H2O.ai
Author-email: sales@h2o.ai
License: Proprietary License
Project-URL: Documentation, https://docs.h2o.ai/h2o_autodoc/latest-stable/userguide/index.html
Keywords: machine learning,data science,automated model documentation,h2o,autodoc,h2o-3,sklearn
Classifier: Development Status :: 5 - Production/Stable
Classifier: Programming Language :: Python :: 3.7
Classifier: Programming Language :: Python :: 3.8
Classifier: Programming Language :: Python :: 3.9
Classifier: Programming Language :: Python :: 3.10
Requires-Python: >=3.7,<3.11
License-File: LICENSE
Requires-Dist: docxtpl ==0.10.0
Requires-Dist: python-docx ==0.8.11
Requires-Dist: matplotlib >=3.2.1
Requires-Dist: jinja2 ==3.1.2
Requires-Dist: pandas ==1.2.5
Requires-Dist: numpy >=1.19.5
Requires-Dist: tabulate ==0.9.0
Requires-Dist: psutil ==5.8.0
Requires-Dist: MarkupSafe ==2.1.2
Requires-Dist: cryptography ==41.0.3
Requires-Dist: boto3 >=1.9.201
Requires-Dist: urllib3 >=1.26.5
Requires-Dist: requests ==2.31.0
Requires-Dist: scipy <=1.10.1
Requires-Dist: seaborn ==0.11.0
Requires-Dist: Cython ==0.29.21 ; python_version < "3.10"
Requires-Dist: scikit-learn ==0.24.2 ; python_version < "3.10"
Requires-Dist: importlib-metadata <5.0.0 ; python_version < "3.8"
Requires-Dist: Cython ==0.29.24 ; python_version == "3.10"
Requires-Dist: scikit-learn ==1.0.2 ; python_version == "3.10"
